kamiwaza_client/__init__.py
kamiwaza_sdk/__init__.py
kamiwaza_sdk/authentication.py
kamiwaza_sdk/cli.py
kamiwaza_sdk/client.py
kamiwaza_sdk/config.py
kamiwaza_sdk/exceptions.py
kamiwaza_sdk/model_selector.py
kamiwaza_sdk/py.typed
kamiwaza_sdk/token_store.py
kamiwaza_sdk/artifacts/providers.py
kamiwaza_sdk/schemas/__init__.py
kamiwaza_sdk/schemas/activity.py
kamiwaza_sdk/schemas/apps.py
kamiwaza_sdk/schemas/auth.py
kamiwaza_sdk/schemas/authz.py
kamiwaza_sdk/schemas/catalog.py
kamiwaza_sdk/schemas/cluster.py
kamiwaza_sdk/schemas/embedding.py
kamiwaza_sdk/schemas/guide.py
kamiwaza_sdk/schemas/ingestion.py
kamiwaza_sdk/schemas/lab.py
kamiwaza_sdk/schemas/prompts.py
kamiwaza_sdk/schemas/retrieval.py
kamiwaza_sdk/schemas/tools.py
kamiwaza_sdk/schemas/vectordb.py
kamiwaza_sdk/schemas/models/__init__.py
kamiwaza_sdk/schemas/models/downloads.py
kamiwaza_sdk/schemas/models/model.py
kamiwaza_sdk/schemas/models/model_family.py
kamiwaza_sdk/schemas/models/model_file.py
kamiwaza_sdk/schemas/models/model_search.py
kamiwaza_sdk/schemas/serving/__init__.py
kamiwaza_sdk/schemas/serving/inference.py
kamiwaza_sdk/schemas/serving/prompt_format.py
kamiwaza_sdk/schemas/serving/serving.py
kamiwaza_sdk/services/__init__.py
kamiwaza_sdk/services/activity.py
kamiwaza_sdk/services/apps.py
kamiwaza_sdk/services/auth.py
kamiwaza_sdk/services/authz.py
kamiwaza_sdk/services/base_service.py
kamiwaza_sdk/services/catalog.py
kamiwaza_sdk/services/cluster.py
kamiwaza_sdk/services/embedding.py
kamiwaza_sdk/services/ingestion.py
kamiwaza_sdk/services/lab.py
kamiwaza_sdk/services/openai.py
kamiwaza_sdk/services/prompts.py
kamiwaza_sdk/services/retrieval.py
kamiwaza_sdk/services/serving.py
kamiwaza_sdk/services/tools.py
kamiwaza_sdk/services/vectordb.py
kamiwaza_sdk/services/models/__init__.py
kamiwaza_sdk/services/models/base.py
kamiwaza_sdk/services/models/compatibility.py
kamiwaza_sdk/services/models/configs.py
kamiwaza_sdk/services/models/downloads.py
kamiwaza_sdk/services/models/files.py
kamiwaza_sdk-0.9.3.dist-info/licenses/LICENSE
kamiwaza_sdk-0.9.3.dist-info/METADATA
kamiwaza_sdk-0.9.3.dist-info/WHEEL
kamiwaza_sdk-0.9.3.dist-info/top_level.txt
kamiwaza_sdk-0.9.3.dist-info/RECORD
