Metadata-Version: 2.4
Name: kamiwaza-sdk
Version: 0.9.3
Summary: Python client library for the Kamiwaza AI Platform
Author-email: Kamiwaza Team <eng@kamiwaza.ai>
License-Expression: MIT
Project-URL: Homepage, https://github.com/kamiwaza/kamiwaza-sdk
Classifier: Development Status :: 4 - Beta
Classifier: Intended Audience :: Developers
Classifier: Operating System :: OS Independent
Classifier: Programming Language :: Python :: 3
Classifier: Programming Language :: Python :: 3.10
Classifier: Programming Language :: Python :: 3.11
Classifier: Topic :: Software Development :: Libraries :: Python Modules
Classifier: Topic :: Scientific/Engineering :: Artificial Intelligence
Requires-Python: >=3.10
License-File: LICENSE
Requires-Dist: requests
Requires-Dist: pydantic[email]
Requires-Dist: httpx
Requires-Dist: openai>=1.0
Requires-Dist: huggingface_hub>=0.23
Dynamic: license-file
